Workbook

Sheet README
A1: Деревья — учёт заказов
A3: Как открыть в Google Sheets
A4: 1. Загрузите этот файл на Google Диск (drive.google.com).
A5: 2. ПКМ → Открыть с помощью → Google Таблицы.
A6: 3. Файл → Сохранить как таблицу Google (чтобы формулы QUERY на Сводке работали нативно).
A7: 4. Настройки доступа → Добавить penalovan@gmail.com (редактор) или «Все, у кого есть ссылка» → Редактор.
A9: Листы: Заказы | Позиции | Прайс | Платежи | Сводка | Менеджеры
A10: Цены в Позициях — снимок; прайс отдельно. Оплаты только через Платежи (нал / р/с).
A11: Документация: docs/google-sheets-structure.md в Agent Store проекта.

Sheet Заказы
A1: ID заказа | B1: Дата создания | C1: Дата посадки | D1: Клиент | E1: Телефон | F1: Адрес | G1: Источник | H1: Менеджер | I1: Статус | J1: Сумма клиенту | K1: Сумма поставщику | L1: Маржа | M1: Оплачено клиентом | N1: Выплачено поставщику | O1: Долг клиента | P1: Долг поставщику | Q1: Основной канал оплаты | R1: Комментарий
A2: З-014 | B2: 46275 | C2: 46283 | D2: Петрова Анна | E2: +7 916 111-22-33 | F2: Подольск, ул. Ленина 12 | G2: Avito | H2: Дарья | I2: подтверждён | J2: =SUMIF(Позиции!B:B,A2,Позиции!H:H) | K2: =SUMIF(Позиции!B:B,A2,Позиции!G:G) | L2: =J2-K2 | M2: =SUMIFS(Платежи!E:E,Платежи!B:B,A2,Платежи!D:D,"от клиента") | N2: =SUMIFS(Платежи!E:E,Платежи!B:B,A2,Платежи!D:D,"поставщику") | O2: =J2-M2 | P2: =K2-N2 | Q2: смешанно | R2: Предоплата 5000 на р/с; остаток налом при посадке
A3: З-015 | B3: 46277 | C3: 46284 | D3: Сидоров Игорь | E3: +7 903 444-55-66 | F3: Москва, ул. Академика Янгеля 5 к2 | G3: Avito | H3: Наталия | I3: подтверждён | J3: =SUMIF(Позиции!B:B,A3,Позиции!H:H) | K3: =SUMIF(Позиции!B:B,A3,Позиции!G:G) | L3: =J3-K3 | M3: =SUMIFS(Платежи!E:E,Платежи!B:B,A3,Платежи!D:D,"от клиента") | N3: =SUMIFS(Платежи!E:E,Платежи!B:B,A3,Платежи!D:D,"поставщику") | O3: =J3-M3 | P3: =K3-N3 | Q3: на р/с | R3: Отправка СДЭК; нал передать нельзя
A4: З-016 | B4: 46280 | C4: 46285 | D4: Козлова Мария | E4: +7 926 777-88-99 | F4: Щербинка, Садовая 8 | G4: сайт | H4: Дарья | I4: черновик | J4: =SUMIF(Позиции!B:B,A4,Позиции!H:H) | K4: =SUMIF(Позиции!B:B,A4,Позиции!G:G) | L4: =J4-K4 | M4: =SUMIFS(Платежи!E:E,Платежи!B:B,A4,Платежи!D:D,"от клиента") | N4: =SUMIFS(Платежи!E:E,Платежи!B:B,A4,Платежи!D:D,"поставщику") | O4: =J4-M4 | P4: =K4-N4 | Q4: наличка у поставщика | R4: Ждём подтверждение даты
A5: З-017 | B5: 46273 | C5: 46281 | D5: Иванов Пётр | E5: +7 915 222-33-44 | F5: Подольск, Юбилейная 3 | G5: Avito | H5: Наталия | I5: выполнен | J5: =SUMIF(Позиции!B:B,A5,Позиции!H:H) | K5: =SUMIF(Позиции!B:B,A5,Позиции!G:G) | L5: =J5-K5 | M5: =SUMIFS(Платежи!E:E,Платежи!B:B,A5,Платежи!D:D,"от клиента") | N5: =SUMIFS(Платежи!E:E,Платежи!B:B,A5,Платежи!D:D,"поставщику") | O5: =J5-M5 | P5: =K5-N5 | Q5: наличка у поставщика | R5: Посадили 4 туи
A6: З-018 | B6: 46279 | C6: 46286 | D6: Морозова Елена | E6: +7 999 100-20-30 | F6: Климовск, Лесная 17 | G6: Avito | H6: Дарья | I6: подтверждён | J6: =SUMIF(Позиции!B:B,A6,Позиции!H:H) | K6: =SUMIF(Позиции!B:B,A6,Позиции!G:G) | L6: =J6-K6 | M6: =SUMIFS(Платежи!E:E,Платежи!B:B,A6,Платежи!D:D,"от клиента") | N6: =SUMIFS(Платежи!E:E,Платежи!B:B,A6,Платежи!D:D,"поставщику") | O6: =J6-M6 | P6: =K6-N6 | Q6: смешанно | R6: Предоплата на р/с; доплата налом

Sheet Позиции
A1: ID позиции | B1: ID заказа | C1: Растение | D1: Кол-во | E1: Цена поставщика (снимок) | F1: Цена продажи (снимок) | G1: Сумма поставщику | H1: Сумма клиенту | I1: Маржа строки | J1: Примечание
A2: П-031 | B2: З-014 | C2: Туя западная Smaragd 80–100 | D2: 4 | E2: 1800 | F2: 3200 | G2: =D2*E2 | H2: =D2*F2 | I2: =H2-G2 | J2: высота 80-100 см
A3: П-032 | B3: З-014 | C3: Гортензия метельчатая Limelight | D3: 2 | E3: 900 | F3: 1800 | G3: =D3*E3 | H3: =D3*F3 | I3: =H3-G3
A4: П-033 | B4: З-015 | C4: Ель обыкновенная 1.2–1.5 м | D4: 1 | E4: 4500 | F4: 7900 | G4: =D4*E4 | H4: =D4*F4 | I4: =H4-G4 | J4: отправка СДЭК
A5: П-034 | B5: З-016 | C5: Туя западная Smaragd 80–100 | D5: 2 | E5: 1800 | F5: 3200 | G5: =D5*E5 | H5: =D5*F5 | I5: =H5-G5 | J5: черновик
A6: П-035 | B6: З-017 | C6: Туя западная Smaragd 80–100 | D6: 4 | E6: 1800 | F6: 3200 | G6: =D6*E6 | H6: =D6*F6 | I6: =H6-G6
A7: П-036 | B7: З-018 | C7: Гортензия метельчатая Limelight | D7: 10 | E7: 900 | F7: 1800 | G7: =D7*E7 | H7: =D7*F7 | I7: =H7-G7 | J7: партия для живой изгороди

Sheet Прайс
A1: ID | B1: Название | C1: Ед. | D1: Цена поставщика | E1: Цена продажи | F1: Маржа ед. | G1: Активен | H1: Дата обновления | I1: Кто обновил | J1: Примечание
A2: R-012 | B2: Туя западная Smaragd 80–100 | C2: шт | D2: 1800 | E2: 3200 | F2: =E2-D2 | G2: да | H2: 46266 | I2: поставщик
A3: R-045 | B3: Ель обыкновенная 1.2–1.5 м | C3: шт | D3: 4500 | E3: 7900 | F3: =E3-D3 | G3: да | H3: 46270 | I3: поставщик | J3: цена выросла с 4200
A4: R-078 | B4: Гортензия метельчатая Limelight | C4: шт | D4: 900 | E4: 1800 | F4: =E4-D4 | G4: да | H4: 46254 | I4: Дарья
A5: R-091 | B5: Спирея японская Goldflame | C5: шт | D5: 450 | E5: 950 | F5: =E5-D5 | G5: да | H5: 46275 | I5: поставщик
A6: R-102 | B6: Клён остролистный 2.0–2.5 м | C6: шт | D6: 6500 | E6: 11000 | F6: =E6-D6 | G6: да | H6: 46268 | I6: Наталия | J6: редкая позиция
A7: R-110 | B7: Барбарис Тунберга Atropurpurea | C7: шт | D7: 350 | E7: 750 | F7: =E7-D7 | G7: нет | H7: 46277 | I7: поставщик | J7: нет в наличии

Sheet Платежи
A1: ID платежа | B1: ID заказа | C1: Дата | D1: Тип | E1: Сумма | F1: Куда / откуда | G1: Кто зафиксировал | H1: Комментарий
A2: ОПЛ-018 | B2: З-017 | C2: 46281 | D2: от клиента | E2: 12800 | F2: наличка у поставщика | G2: Наталия | H2: полная оплата при посадке
A3: ОПЛ-019 | B3: З-017 | C3: 46281 | D3: поставщику | E3: 7200 | F3: наличка у поставщика | G3: Наталия | H3: закуп оставлен поставщику
A4: ОПЛ-020 | B4: З-014 | C4: 46275 | D4: от клиента | E4: 5000 | F4: на р/с | G4: Дарья | H4: предоплата
A5: ОПЛ-021 | B5: З-014 | C5: 46283 | D5: от клиента | E5: 11400 | F5: наличка у поставщика | G5: Дарья | H5: доплата при посадке
A6: ОПЛ-022 | B6: З-014 | C6: 46283 | D6: поставщику | E6: 9000 | F6: наличка у поставщика | G6: Дарья | H6: закуп за туи и гортензии
A7: ОПЛ-023 | B7: З-015 | C7: 46277 | D7: от клиента | E7: 7900 | F7: на р/с | G7: Наталия | H7: оплата до отправки СДЭК
A8: ОПЛ-024 | B8: З-018 | C8: 46279 | D8: от клиента | E8: 5000 | F8: на р/с | G8: Дарья | H8: предоплата; остаток 13000 при посадке

Sheet Сводка
A1: День поставщика
A2: Дата дня | B2: 46283
A3: Заказы на дату (QUERY — работает в Google Sheets после загрузки)
A4: =QUERY(Заказы!A:R,"select A,C,D,E,F,J,K,Q where C = date '"&TEXT(B2,"yyyy-mm-dd")&"' and I <> 'отменён' order by F",1)
A6: Деньги
A7: Показатель | B7: Значение
A8: Выручка (выполненные) | B8: =SUMIF(Заказы!I:I,"выполнен",Заказы!J:J)
A9: Закуп (выполненные) | B9: =SUMIF(Заказы!I:I,"выполнен",Заказы!K:K)
A10: Маржа выполненных | B10: =B8-B9
A11: Долг клиентов всего | B11: =SUMIF(Заказы!I:I,"<>отменён",Заказы!O:O)
A12: Долг поставщику всего | B12: =SUMIF(Заказы!I:I,"<>отменён",Заказы!P:P)
A13: Обороты: наличка у поставщика | B13: =SUMIF(Платежи!F:F,"наличка у поставщика",Платежи!E:E)
A14: Обороты: на р/с | B14: =SUMIF(Платежи!F:F,"на р/с",Платежи!E:E)
A16: Подсказка: в Excel QUERY не работает — смотрите фильтр на листе Заказы по дате посадки. В Google Sheets QUERY заработает после File → Import / Open.

Sheet Менеджеры
A1: Срез по менеджерам (чистыми = маржа). Без отменённых. Период опционален: если B/C пустые — все даты.
A2: Менеджер | B2: Период с | C2: Период по | D2: Продажи (сумма клиенту) | E2: Закуп поставщику | F2: Чистыми (маржа) | G2: Число заказов
A3: Наталия | D3: =IF(AND(B3="",C3=""),SUMIFS(Заказы!J:J,Заказы!H:H,A3,Заказы!I:I,"<>отменён"),SUMIFS(Заказы!J:J,Заказы!H:H,A3,Заказы!I:I,"<>отменён",Заказы!C:C,">="&B3,Заказы!C:C,"<="&C3)) | E3: =IF(AND(B3="",C3=""),SUMIFS(Заказы!K:K,Заказы!H:H,A3,Заказы!I:I,"<>отменён"),SUMIFS(Заказы!K:K,Заказы!H:H,A3,Заказы!I:I,"<>отменён",Заказы!C:C,">="&B3,Заказы!C:C,"<="&C3)) | F3: =D3-E3 | G3: =IF(AND(B3="",C3=""),COUNTIFS(Заказы!H:H,A3,Заказы!I:I,"<>отменён"),COUNTIFS(Заказы!H:H,A3,Заказы!I:I,"<>отменён",Заказы!C:C,">="&B3,Заказы!C:C,"<="&C3))
A4: Дарья | D4: =IF(AND(B4="",C4=""),SUMIFS(Заказы!J:J,Заказы!H:H,A4,Заказы!I:I,"<>отменён"),SUMIFS(Заказы!J:J,Заказы!H:H,A4,Заказы!I:I,"<>отменён",Заказы!C:C,">="&B4,Заказы!C:C,"<="&C4)) | E4: =IF(AND(B4="",C4=""),SUMIFS(Заказы!K:K,Заказы!H:H,A4,Заказы!I:I,"<>отменён"),SUMIFS(Заказы!K:K,Заказы!H:H,A4,Заказы!I:I,"<>отменён",Заказы!C:C,">="&B4,Заказы!C:C,"<="&C4)) | F4: =D4-E4 | G4: =IF(AND(B4="",C4=""),COUNTIFS(Заказы!H:H,A4,Заказы!I:I,"<>отменён"),COUNTIFS(Заказы!H:H,A4,Заказы!I:I,"<>отменён",Заказы!C:C,">="&B4,Заказы!C:C,"<="&C4))
A5: Итого | D5: =D3+D4 | E5: =E3+E4 | F5: =F3+F4 | G5: =G3+G4
A7: Пример с периодом: укажите в B3/C3 даты посадки (например 2026-09-01 … 2026-09-30) — цифры пересчитаются.
